setup.py
distributions_ev/Binomialdistribution.py
distributions_ev/Gaussiandistribution.py
distributions_ev/Generaldistribution.py
distributions_ev/__init__.py
distributions_ev.egg-info/PKG-INFO
distributions_ev.egg-info/SOURCES.txt
distributions_ev.egg-info/dependency_links.txt
distributions_ev.egg-info/not-zip-safe
distributions_ev.egg-info/top_level.txt